{
    "themes": [
        {
            "themeId": "58e7782f-0fd0-4d88-bf02-0f411b7941d9",
            "themeDisplayName": "Vaalea"
        },
        {
            "themeId": "030a2d55-64d3-44b7-b66f-4896a33d6fd3",
            "themeDisplayName": "Tumma"
        },
        {
            "themeId": "42f08b65-a6b1-44b7-bae2-c998e009c5c5",
            "themeDisplayName": "Suuri kontrasti"
        }
    ],
    "displayName": "RingCentral mit Telekom",
    "salutationName": "RingCentral mit Telekom Team",
    "notificationAppPrefixName": "RingCentral mit Telekom",
    "glipName": "Glip",
    "notificationVideoBridgeName": "RingCentral mit Telekom Video -tapaaminen",
    "notificationTradeMark": "Telekom on Telekom Deutschland GmbH:n rekisteröity tavaramerkki.",
    "companyBillingName": "RingCentral, Inc",
    "shortDisplayName": "Telekom",
    "copyright": "RingCentral, Inc. Kaikki oikeudet pidätetään.",
    "videoProductName": "RingCentral mit Telekom Video",
    "mvpProductName": "RingCentral-sovellus",
    "officeDisplayName": "RingCentral mit Telekom",
    "businessInformationVerificationHelpPage": "https://support.ringcentral.com/article-v2/Providing-documentation-for-business-information-verification.html?brand=RingCentral&product=MVP&language=en_US"
}